lancer/__init__.py
lancer/_cloudflare.py
lancer/_common.py
lancer/_gandi.py
lancer/_impl.py
lancer-0.4.0.dist-info/entry_points.txt
lancer-0.4.0.dist-info/LICENSE
lancer-0.4.0.dist-info/WHEEL
lancer-0.4.0.dist-info/METADATA
lancer-0.4.0.dist-info/RECORD
