Metadata-Version: 2.1
Name: lancer
Version: 0.4.0
Summary: Provision TLS *Cer*tificates for your *LAN*, using the ACME DNS challenge.
Home-page: https://github.com/glyph/lancer
License: UNKNOWN
Author: Glyph
Author-email: glyph@twistedmatrix.com
Classifier: License :: OSI Approved :: MIT License
Requires-Dist: attrs>=18.1.0
Requires-Dist: secretly>=0.2
Requires-Dist: treq>=18.6.0
Requires-Dist: txacme[libcloud]>=0.9.2
Requires-Dist: twisted[tls]>=18.7.0
Provides-Extra: .none
